{
	"configurations" : 
	[
		{
			"directories" : 
			[
				{
					"build" : ".",
					"hasInstallRule" : true,
					"jsonFile" : "directory-.-Debug-874d246cd16c5bcc5417.json",
					"minimumCMakeVersion" : 
					{
						"string" : "3.16"
					},
					"projectIndex" : 0,
					"source" : ".",
					"targetIndexes" : 
					[
						0,
						1,
						2
					]
				}
			],
			"name" : "Debug",
			"projects" : 
			[
				{
					"directoryIndexes" : 
					[
						0
					],
					"name" : "AI_Mobile_Test_Studio",
					"targetIndexes" : 
					[
						0,
						1,
						2
					]
				}
			],
			"targets" : 
			[
				{
					"directoryIndex" : 0,
					"id" : "AI_Mobile_Test_Studio::@6890427a1f51a3e7e1df",
					"jsonFile" : "target-AI_Mobile_Test_Studio-Debug-284a582bcfe9ea6c74a6.json",
					"name" : "AI_Mobile_Test_Studio",
					"projectIndex" : 0
				},
				{
					"directoryIndex" : 0,
					"id" : "AI_Mobile_Test_Studio_autogen::@6890427a1f51a3e7e1df",
					"jsonFile" : "target-AI_Mobile_Test_Studio_autogen-Debug-db08a01ef6e4913651da.json",
					"name" : "AI_Mobile_Test_Studio_autogen",
					"projectIndex" : 0
				},
				{
					"directoryIndex" : 0,
					"id" : "AI_Mobile_Test_Studio_autogen_timestamp_deps::@6890427a1f51a3e7e1df",
					"jsonFile" : "target-AI_Mobile_Test_Studio_autogen_timestamp_deps-Debug-4ef871999b823c448ee2.json",
					"name" : "AI_Mobile_Test_Studio_autogen_timestamp_deps",
					"projectIndex" : 0
				}
			]
		}
	],
	"kind" : "codemodel",
	"paths" : 
	{
		"build" : "E:/Project/AI_Mobile_Test_Studio/build",
		"source" : "E:/Project/AI_Mobile_Test_Studio"
	},
	"version" : 
	{
		"major" : 2,
		"minor" : 7
	}
}
